openfec_sdk/__init__.py
openfec_sdk/api_client.py
openfec_sdk/configuration.py
openfec_sdk/exceptions.py
openfec_sdk/model_utils.py
openfec_sdk/rest.py
openfec_sdk/api/__init__.py
openfec_sdk/api/audit_api.py
openfec_sdk/api/candidate_api.py
openfec_sdk/api/committee_api.py
openfec_sdk/api/communication_cost_api.py
openfec_sdk/api/dates_api.py
openfec_sdk/api/debts_api.py
openfec_sdk/api/disbursements_api.py
openfec_sdk/api/efiling_api.py
openfec_sdk/api/electioneering_api.py
openfec_sdk/api/filer_resources_api.py
openfec_sdk/api/filings_api.py
openfec_sdk/api/financial_api.py
openfec_sdk/api/independent_expenditures_api.py
openfec_sdk/api/legal_api.py
openfec_sdk/api/loans_api.py
openfec_sdk/api/party_coordinated_expenditures_api.py
openfec_sdk/api/presidential_api.py
openfec_sdk/api/receipts_api.py
openfec_sdk/api/search_api.py
openfec_sdk/models/__init__.py
openfec_sdk/models/audit_candidate_search.py
openfec_sdk/models/audit_candidate_search_list.py
openfec_sdk/models/audit_case.py
openfec_sdk/models/audit_case_category_relation.py
openfec_sdk/models/audit_case_category_relation_page.py
openfec_sdk/models/audit_case_page.py
openfec_sdk/models/audit_case_sub_category.py
openfec_sdk/models/audit_case_sub_category_page.py
openfec_sdk/models/audit_category.py
openfec_sdk/models/audit_category_page.py
openfec_sdk/models/audit_category_relation.py
openfec_sdk/models/audit_category_relation_page.py
openfec_sdk/models/audit_committee_search.py
openfec_sdk/models/audit_committee_search_list.py
openfec_sdk/models/audit_primary_category.py
openfec_sdk/models/audit_primary_category_page.py
openfec_sdk/models/base_f3_filing.py
openfec_sdk/models/base_f3_filing_page.py
openfec_sdk/models/base_f3_p_filing.py
openfec_sdk/models/base_f3_p_filing_page.py
openfec_sdk/models/base_f3_x_filing.py
openfec_sdk/models/base_f3_x_filing_page.py
openfec_sdk/models/calendar_date.py
openfec_sdk/models/calendar_date_page.py
openfec_sdk/models/candidate.py
openfec_sdk-0.2.0.dist-info/METADATA
openfec_sdk-0.2.0.dist-info/WHEEL
openfec_sdk-0.2.0.dist-info/top_level.txt
openfec_sdk-0.2.0.dist-info/RECORD
