Metadata-Version: 2.1
Name: openfec-sdk
Version: 0.2.0
Summary: OpenFEC SDK
Home-page: https://github.com/rhythmictech/openFEC-python-sdk
Author-email: opensource@rhythmictech.com
License: UNKNOWN
Keywords: Swagger,OpenFEC
Platform: UNKNOWN
Requires-Dist: certifi (>=14.05.14)
Requires-Dist: python-dateutil (>=2.5.3)
Requires-Dist: setuptools (>=21.0.0)
Requires-Dist: six (>=1.10)
Requires-Dist: urllib3 (>=1.15.1)
Requires-Dist: future ; python_version <= "2.7"
